gitdb/__init__.py
gitdb/loader.py
gitdb/main.py
gitdb/api/__init__.py
gitdb/api/client.py
gitdb/dao/__init__.py
gitdb/dao/contributors.py
gitdb/dao/core.py
gitdb/dao/issues.py
gitdb/dao/models.py
gitdb/dao/reviews.py
gitdb/dao/stars.py
gitdb/dao/weekly_commits.py
venv/bin/rst2html.py
venv/bin/rst2html4.py
venv/bin/rst2html5.py
venv/bin/rst2latex.py
venv/bin/rst2man.py
venv/bin/rst2odt.py
venv/bin/rst2odt_prepstyles.py
venv/bin/rst2pseudoxml.py
venv/bin/rst2s5.py
venv/bin/rst2xetex.py
venv/bin/rst2xml.py
venv/bin/rstpep2html.py
PyGitDB-0.1.0.dist-info/LICENSE
PyGitDB-0.1.0.dist-info/METADATA
PyGitDB-0.1.0.dist-info/WHEEL
PyGitDB-0.1.0.dist-info/entry_points.txt
PyGitDB-0.1.0.dist-info/top_level.txt
PyGitDB-0.1.0.dist-info/zip-safe
PyGitDB-0.1.0.dist-info/RECORD
