Metadata-Version: 2.1
Name: PyGitDB
Version: 0.1.0
Summary: Load git stats into a DuckDB db locally for easy analytics.
Home-page: UNKNOWN
License: UNKNOWN
Platform: UNKNOWN
Requires-Python: >=3.9
License-File: LICENSE
Requires-Dist: SQLAlchemy (~=1.4)
Requires-Dist: duckdb-engine
Requires-Dist: duckdb
Requires-Dist: pydantic
Requires-Dist: pandas
Requires-Dist: requests
Requires-Dist: loguru
Provides-Extra: dev
Requires-Dist: pre-commit ; extra == 'dev'
Requires-Dist: pycln ; extra == 'dev'
Requires-Dist: ruff ; extra == 'dev'
Requires-Dist: isort ; extra == 'dev'
Requires-Dist: black ; extra == 'dev'
